pyvds/__init__.py
pyvds/accessors.py
pyvds/open.py
pyvds/read.py
pyvds/tools.py
pyvds-0.0.3.dist-info/LICENSE.txt
pyvds-0.0.3.dist-info/METADATA
pyvds-0.0.3.dist-info/WHEEL
pyvds-0.0.3.dist-info/top_level.txt
pyvds-0.0.3.dist-info/RECORD
