Metadata-Version: 2.1
Name: pyvds
Version: 0.0.3
Summary: Convenience wrapper around OpenVDS+ Python bindings
Home-page: https://github.com/equinor/pyvds
Author: equinor
License: UNKNOWN
Platform: UNKNOWN
License-File: LICENSE.txt
Requires-Dist: openvds
Requires-Dist: numpy
Requires-Dist: segyio
